_aliyun
aliyun
