Metadata-Version: 1.0
Name: Aliyun
Version: 0.1.1
Summary: UNKNOWN
Home-page: http://ods.aliyun.com/
Author: Jay Su
Author-email: shijie.susj@aliyun-inc.com
License: BSD
Platform: ALL
Classifier: Development Status :: 1 - Planning
Classifier: Environment :: Console
Classifier: Intended Audience :: Developers
Classifier: License :: OSI Approved :: BSD License
Classifier: Natural Language :: English
Classifier: Operating System :: MacOS :: MacOS X
Classifier: Operating System :: Microsoft :: Windows
Classifier: Operating System :: POSIX :: BSD
Classifier: Operating System :: POSIX :: Linux
Classifier: Programming Language :: Python :: 2.6
Classifier: Programming Language :: Python :: 2.7
Classifier: Topic :: Software Development
Classifier: Topic :: Utilities
